cloud_ranges/__init__.py
cloud_ranges/__main__.py
cloud_ranges/aws_db.py
cloud_ranges/azure_db.py
cloud_ranges/db_common.py
cloud_ranges/db_dir.py
cloud_ranges/digitalocean_db.py
cloud_ranges/gcp_db.py
cloud_ranges/ibm_db.py
cloud_ranges/oracle_db.py
cloud_ranges/range_db.py
cloud_ranges/utils.py
cloud_ranges/version.py
cloud_ranges-0.0.4.dist-info/LICENSE
cloud_ranges-0.0.4.dist-info/METADATA
cloud_ranges-0.0.4.dist-info/WHEEL
cloud_ranges-0.0.4.dist-info/entry_points.txt
cloud_ranges-0.0.4.dist-info/top_level.txt
cloud_ranges-0.0.4.dist-info/RECORD
