Metadata-Version: 2.1
Name: cloud-ranges
Version: 0.0.4
Summary: Discover if IP belongs cloud providers ranges
Home-page: https://gitlab.com/Zer1t0/cloud-ranges
Author: Eloy Pérez González
Classifier: Programming Language :: Python :: 3
Classifier: License :: OSI Approved :: GNU General Public License v3 (GPLv3)
License-File: LICENSE
Requires-Dist: tqdm
Requires-Dist: pandas
Requires-Dist: requests
Requires-Dist: bs4
